github_repo_manager/__init__.py
github_repo_manager/__main__.py
github_repo_manager/cli.py
github_repo_manager/core.py
github_repository_manager-0.1.1.dist-info/METADATA
github_repository_manager-0.1.1.dist-info/WHEEL
github_repository_manager-0.1.1.dist-info/entry_points.txt
github_repository_manager-0.1.1.dist-info/top_level.txt
github_repository_manager-0.1.1.dist-info/RECORD
