Metadata-Version: 2.2
Name: github-repository-manager
Version: 0.1.1
Summary: A CLI tool to manage GitHub repositories with interactive features
Home-page: https://github.com/conficiusa/github-repository-manager
Author: conficiusa
Author-email: addawebadua@example.com
Classifier: Programming Language :: Python :: 3
Classifier: License :: OSI Approved :: MIT License
Classifier: Operating System :: OS Independent
Requires-Python: >=3.6
Requires-Dist: requests
Requires-Dist: blessed
Dynamic: author
Dynamic: author-email
Dynamic: classifier
Dynamic: description
Dynamic: description-content-type
Dynamic: home-page
Dynamic: requires-dist
Dynamic: requires-python
Dynamic: summary
